flask_ligand/__init__.py
flask_ligand/cli.py
flask_ligand/controllers.py
flask_ligand/default_settings.py
flask_ligand/schemas.py
flask_ligand/extensions/__init__.py
flask_ligand/extensions/api.py
flask_ligand/extensions/database.py
flask_ligand/extensions/jwt.py
flask_ligand/views/__init__.py
flask_ligand/views/openapi.py
flask_ligand/views/common/__init__.py
flask_ligand/views/common/openapi_doc.py
lask_ligand-0.7.0.dist-info/AUTHORS
lask_ligand-0.7.0.dist-info/LICENSE
lask_ligand-0.7.0.dist-info/METADATA
lask_ligand-0.7.0.dist-info/WHEEL
lask_ligand-0.7.0.dist-info/top_level.txt
lask_ligand-0.7.0.dist-info/RECORD
